patten_pk/__init__.py
patten_pk/pattern.py
pattern_pk-0.1.0.dist-info/LICENSE
pattern_pk-0.1.0.dist-info/METADATA
pattern_pk-0.1.0.dist-info/WHEEL
pattern_pk-0.1.0.dist-info/top_level.txt
pattern_pk-0.1.0.dist-info/RECORD
