Metadata-Version: 2.1
Name: pattern_pk
Version: 0.1.0
Summary: This Package is for printing patterns
Home-page: https://github.com/prachikabra121/Pattern
Author: Prachi Kabra
Author-email: codebakery8889@gmail.com
Classifier: Programming Language :: Python :: 3
Classifier: License :: OSI Approved :: MIT License
Classifier: Operating System :: OS Independent
Requires-Python: >=3.6
License-File: LICENSE
